{"index":"110719032","imgurl":"https://live.staticflickr.com/2760/4327815584_f2fcc8e781_b.jpg","name":"GUNDAM","info":"","photoNum":"19","videoNum":"","viewNum":"53","author":"RYU","authorImg":"https://live.staticflickr.com/55/buddyicons/72349620@N00_l.jpg?1340426522#72349620@N00)","images":[{"ID":"1","imgurl":"https://live.staticflickr.com/2760/4327815584_f2fcc8e781_b.jpg","title":"GUNDAM","author":"RYU","likeNum":"20","commentNum":"4"},{"ID":"2","imgurl":"https://live.staticflickr.com/4035/4327084007_ff3c085b1c_c.jpg","title":"GUNDAM","author":"RYU","likeNum":"10","commentNum":"0"},{"ID":"3","imgurl":"https://live.staticflickr.com/2772/4327815910_4827cb5235_c.jpg","title":"GUNDAM","author":"RYU","likeNum":"0","commentNum":"0"},{"ID":"4","imgurl":"https://live.staticflickr.com/4019/4327084263_46c5e6c7d9_c.jpg","title":"GUNDAM","author":"RYU","likeNum":"25","commentNum":"2"},{"ID":"5","imgurl":"https://live.staticflickr.com/2715/4327084353_f505c9da7a_c.jpg","title":"GUNDAM","author":"RYU","likeNum":"4","commentNum":"0"},{"ID":"6","imgurl":"https://live.staticflickr.com/4067/4327084449_76c340eca7_c.jpg","title":"GUNDAM","author":"RYU","likeNum":"4","commentNum":"0"},{"ID":"7","imgurl":"https://live.staticflickr.com/4041/4327084543_44710c341e_c.jpg","title":"GUNDAM","author":"RYU","likeNum":"1","commentNum":"0"},{"ID":"8","imgurl":"https://live.staticflickr.com/4069/4327084647_0a8f6d8e77_c.jpg","title":"GUNDAM","author":"RYU","likeNum":"1","commentNum":"0"},{"ID":"9","imgurl":"https://live.staticflickr.com/2795/4327816472_11cda8482c_c.jpg","title":"GUNDAM","author":"RYU","likeNum":"2","commentNum":"0"},{"ID":"10","imgurl":"https://live.staticflickr.com/2693/4327816582_50b7a084ac_c.jpg","title":"GUNDAM","author":"RYU","likeNum":"25","commentNum":"8"},{"ID":"11","imgurl":"https://live.staticflickr.com/4059/4327084983_e4133d0dce_c.jpg","title":"GUNDAM","author":"RYU","likeNum":"1","commentNum":"0"},{"ID":"12","imgurl":"https://live.staticflickr.com/4069/4327816778_d1ffab8953_c.jpg","title":"GUNDAM","author":"RYU","likeNum":"11","commentNum":"0"},{"ID":"13","imgurl":"https://live.staticflickr.com/4015/4327085191_3e8a52be16_c.jpg","title":"GUNDAM","author":"RYU","likeNum":"2","commentNum":"0"},{"ID":"14","imgurl":"https://live.staticflickr.com/4005/4327085355_cebb259d9e_c.jpg","title":"GUNDAM","author":"RYU","likeNum":"3","commentNum":"0"},{"ID":"15","imgurl":"https://live.staticflickr.com/2732/4327085475_6421962d96_c.jpg","title":"GUNDAM","author":"RYU","likeNum":"0","commentNum":"0"},{"ID":"16","imgurl":"https://live.staticflickr.com/2683/4327817234_a3259814bc_c.jpg","title":"GUNDAM","author":"RYU","likeNum":"5","commentNum":"1"},{"ID":"17","imgurl":"https://live.staticflickr.com/2752/4327817364_2a5aef79b7_w.jpg","title":"GUNDAM","author":"RYU","likeNum":"4","commentNum":"0"},{"ID":"18","imgurl":"https://live.staticflickr.com/2790/4327085843_2b8c3ca3f5_z.jpg","title":"GUNDAM","author":"RYU","likeNum":"0","commentNum":"0"},{"ID":"19","imgurl":"https://live.staticflickr.com/1058/5114919567_201e14fb0e_c.jpg","title":"GUNDAM","author":"RYU","likeNum":"1","commentNum":"3"}]}